{
	"name": "Company Slider",
	"version": "1.0",
	"release_date": "2023-03-28",
	"license": "MIT",
	"price_usd": "0",
	"download_url": "https://github.com/multicolor-rgb/company-slider-for-bludit-cms/archive/refs/tags/1.0.zip",
	"demo_url": "",
	"information_url": "https://github.com/multicolor-rgb/company-slider-for-bludit-cms/releases/tag/1.0",
	"description": "Carousel creator for logos yours partner.",
	"features": {
		"0": "TinyMCE shortode support.",
		"1": "PHP function for template support.",
		"2": "Easy to use and many settings option.",
		"3": "Based on slick.js"
	},
	"description_de": "",
	"features_de": {
	},
	"description_es": "",
	"features_es": {
	},
	"description_ru": "Создаёт галерею в виде карусели с логотипами ваших партнёров или с подборкой изображений заданной вами.",
	"features_ru": {
		"0": "Поддержка шорткода для TinyMCE.",
		"1": "PHP функция для поддержки шаблонов.",
		"2": "Простой в использовании, но с множеством настроек.",
		"3": "Основан на библиотеке slick.js"
	},
	"author_username": "multicolor"
}
