{
  "name": "Announcement",
  "version": "1.1.0",
  "author_username": "tim-moritz",
  "release_date": "2021-12-14",
  "license": "MIT",
  "price_usd": "0",
  "download_url": "https://github.com/gaincoder/announcement/archive/refs/tags/1.0.0.zip",
  "demo_url": "",
  "information_url": "https://github.com/gaincoder/announcement",
  "description": "Shows an announcement banner on the top of each page.",
  "features": {
    "0": "Set HTML content.",
    "1": "Set start and end date/time.",
    "2": "Set border color and width."
  },
  "description_de": "Zeigt einen Ankündigungs-Banner oberhalb jeder Seite.",
  "features_de": {
    "0": "HTML Inhtalt setzen.",
    "1": "Start- und Endzeitpunkt festlegen.",
    "2": "Rahmenfarbe und -breite festlegen."
  },
  "description_es": "Muestra un banner de anuncio en la parte superior de cada página.",
  "features_es": {
    "0": "Establezca contenido en HTML.",
    "1": "Establezca la fecha/hora de inicio y finalización.",
    "2": "Establezca el color y el ancho del borde."
  },
  "description_ru": "Показывает баннер с объявлением в верхней части каждой страницы сайта.",
  "features_ru": {
    "0": "Содержимое баннера может включать HTML теги.",
    "1": "Присутствует установка даты начала и даты окончания для отображения баннера.",
    "2": "Присутствует настройка цвета и ширины рамки (границы) баннера."
  }
}
