{
	"name": "BluSeo",
	"version": "1.2",
	"release_date": "2017-10-26",
	"license": "MIT",
	"price_usd": "0",
	"download_url_v2": "https://github.com/Krakengr/BluSEO/archive/master.zip",
	"demo_url": "",
	"information_url": "https://github.com/Krakengr/BluSEO",
	"description": "The SEO Plugin for Bludit.",
	"features": {
	},
	"description_pt": "O plugin de SEO para Bludit.",
	"features_pt": {
	},	
	"description_de": "Das SEO Plugin für Bludit.",
	"features_de": {
	},
	"description_es": "El complemento SEO para Bludit.",
	"features_es": {
	},
	"description_ru": "Добавляет дополнительные SEO настройки для Bludit.",
	"features_ru": {
	},
	"author_username": "krakengr"
}
