{
	"name": "Auto-Archive-Menu-Plus-More",
	"version": "2.3",
	"release_date": "2018-05-06",
	"license": "MIT",
	"price_usd": "0",
	"download_url": "https://github.com/BlakesHeaven/Auto-Archive-Menu-Plus-More/archive/v2.3.x.zip",
	"demo_url": "",
	"information_url": "https://github.com/BlakesHeaven/Auto-Archive-Menu-Plus-More",
	"description": "Published content moves through three different sections automatically based on the published date.",
	"features": {
		"0": "",
		"1": "",
		"2": ""
	},
	"description_de": "Veröffentlichte Inhalte werden automatisch drei Sektionen zugewiesen, abghängig vom Datum ihrer Veröffentlichung.",
	"features_de": {
		"0": "",
		"1": "",
		"2": ""
	},
	"description_es": "",
	"features_es": {
		"0": "",
		"1": "",
		"2": ""
	},
	"author_username": "blake"
}
